mgefinder/__init__.py
mgefinder/blasttools.py
mgefinder/bowtie2tools.py
mgefinder/bwatools.py
mgefinder/cdhittools.py
mgefinder/clusterseq.py
mgefinder/dependencies.py
mgefinder/embosstools.py
mgefinder/fastatools.py
mgefinder/find.py
mgefinder/formatbam.py
mgefinder/genotype.py
mgefinder/help.py
mgefinder/inferseq.py
mgefinder/inferseqassembly.py
mgefinder/inferseqdatabase.py
mgefinder/inferseqoverlap.py
mgefinder/inferseqreference.py
mgefinder/main.py
mgefinder/makedatabase.py
mgefinder/makefasta.py
mgefinder/misc.py
mgefinder/pair.py
mgefinder/pysamtools.py
mgefinder/recall.py
mgefinder/samtools.py
mgefinder/sctools.py
mgefinder/summarize.py
mgefinder/terminustrie.py
mgefinder/wholegenome.py
mgefinder/workflow.py
mgefinder/workflow/database.original.Snakefile
mgefinder/workflow/database.original.config.yml
mgefinder/workflow/database.sensitive.Snakefile
mgefinder/workflow/database.sensitive.config.yml
mgefinder/workflow/denovo.original.Snakefile
mgefinder/workflow/denovo.original.config.yml
mgefinder/workflow/denovo.sensitive.Snakefile
mgefinder/workflow/denovo.sensitive.config.yml
mgefinder-1.0.6.dist-info/LICENSE.txt
mgefinder-1.0.6.dist-info/METADATA
mgefinder-1.0.6.dist-info/WHEEL
mgefinder-1.0.6.dist-info/entry_points.txt
mgefinder-1.0.6.dist-info/top_level.txt
mgefinder-1.0.6.dist-info/RECORD
