Metadata-Version: 2.1
Name: mgefinder
Version: 1.0.6
Summary: A toolbox for identifying mobile genetic element (MGE) insertions from short-read sequencing data of bacterial isolates.
Home-page: https://github.com/bhattlab/MGEfinder
Author: Matt Durrant
Author-email: mdurrant@stanford.edu
License: MIT
Platform: UNKNOWN
Requires-Dist: click (==7.0)
Requires-Dist: pandas (==0.25.3)
Requires-Dist: biopython (==1.75)
Requires-Dist: pysam (==0.15.3)
Requires-Dist: editdistance
Requires-Dist: scipy (==1.4.0)
Requires-Dist: networkx (==2.4)
Requires-Dist: tqdm (==4.40.2)
